Qcover/__init__.py
Qcover/core.py
Qcover/exceptions.py
Qcover/utils.py
Qcover/version.py
Qcover/applications/__init__.py
Qcover/applications/common.py
Qcover/applications/general_01_programming.py
Qcover/applications/graph_color.py
Qcover/applications/max_2_sat.py
Qcover/applications/max_cut.py
Qcover/applications/minimum_vertex_cover.py
Qcover/applications/number_partition.py
Qcover/applications/qadratic_knapsack.py
Qcover/applications/quadratic_assignment.py
Qcover/applications/set_packing.py
Qcover/applications/set_partitioning.py
Qcover/applications/sherrington_kirkpatrick.py
Qcover/backends/__init__.py
Qcover/backends/backend.py
Qcover/backends/circuitbycirq.py
Qcover/backends/circuitbyprojectq.py
Qcover/backends/circuitbyqiskit.py
Qcover/backends/circuitbyqiskit_statistic.py
Qcover/backends/circuitbyqton.py
Qcover/backends/circuitbyquafu.py
Qcover/backends/circuitbyqulacs.py
Qcover/backends/circuitbytensor.py
Qcover/compiler/__init__.py
Qcover/compiler/compilerforQAOA.py
Qcover/compiler/hardware_library.py
Qcover/optimizers/COBYLA.py
Qcover/optimizers/Fourier.py
Qcover/optimizers/Gradient_Descent.py
Qcover/optimizers/Interp.py
Qcover/optimizers/L_BFGS_B.py
Qcover/optimizers/SHGO.py
Qcover/optimizers/SLSQP.py
Qcover/optimizers/SPSA.py
Qcover/optimizers/Simulated_Annealing.py
Qcover/optimizers/__init__.py
Qcover/optimizers/optimizer.py
Qcover/research/Ent_TMI.py
Qcover/research/GHZ_Generate.py
Qcover/research/QAOA_Generate.py
Qcover/research/__init__.py
Qcover/research/scrambling-OTOC.py
Qcover/simulator/__init__.py
Qcover/simulator/qton.py
Qcover-2.6.0.dist-info/LICENSE
Qcover-2.6.0.dist-info/METADATA
Qcover-2.6.0.dist-info/WHEEL
Qcover-2.6.0.dist-info/top_level.txt
Qcover-2.6.0.dist-info/RECORD
