Metadata-Version: 2.1
Name: Qcover
Version: 2.6.0
Summary: Quantum computing solver
Home-page: https://github.com/BAQIS-Quantum/Qcover
Author: ntyz&finleyzhuang
Author-email: puyn@baqis.ac.cn
License: Apache-2.0 License
Project-URL: Bug Reports, https://github.com/BAQIS-Quantum/Qcover/issues
Project-URL: Source, https://github.com/BAQIS-Quantum/Qcover
Keywords: QAOA based combinational optimization solver QUBO quantum
Classifier: Development Status :: 3 - Alpha
Classifier: Intended Audience :: Developers
Classifier: Intended Audience :: Science/Research
Classifier: Operating System :: Microsoft :: Windows
Classifier: Operating System :: POSIX :: Linux
Classifier: Operating System :: MacOS :: MacOS X
Classifier: Topic :: Scientific/Engineering :: Interface Engine/Protocol Translator
Classifier: Programming Language :: Python
Classifier: Programming Language :: Python :: 3
Classifier: Programming Language :: Python :: 3.8
Classifier: Programming Language :: Python :: 3.9
Requires-Python: >=3.8
License-File: LICENSE
Requires-Dist: qiskit (>=0.33.0)
Requires-Dist: projectq (>=0.6.1.post0)
Requires-Dist: cirq (>=0.13.0)
Requires-Dist: quimb (>=1.3.0)
Requires-Dist: qulacs (>=0.3.0)
Requires-Dist: pyquafu (>=0.3.6)
Provides-Extra: docs
Requires-Dist: Sphinx ; extra == 'docs'
Requires-Dist: sphinxcontrib-napoleon ; extra == 'docs'
Requires-Dist: sphinxcontrib-zopeext ; extra == 'docs'
Provides-Extra: test
Requires-Dist: pytest (>=4.4.0) ; extra == 'test'
